LICENSE
MANIFEST.in
README.rst
setup.py
django_registration_bootstrap.egg-info/PKG-INFO
django_registration_bootstrap.egg-info/SOURCES.txt
django_registration_bootstrap.egg-info/dependency_links.txt
django_registration_bootstrap.egg-info/not-zip-safe
django_registration_bootstrap.egg-info/requires.txt
django_registration_bootstrap.egg-info/top_level.txt
registration_bootstrap/__init__.py
registration_bootstrap/models.py
registration_bootstrap/templates/registration/activate.html
registration_bootstrap/templates/registration/activation_complete.html
registration_bootstrap/templates/registration/registration_complete.html
registration_bootstrap/templates/registration/registration_form.html