Metadata-Version: 1.0
Name: django-registration-bootstrap
Version: 0.2.0
Summary: Bootstrap implementation for Django registration.
Home-page: http://github.com/pydanny/django-registration-bootstrap
Author: Daniel Greenfeld
Author-email: pydanny@gmail.com
License: MIT
Keywords: django
Platform: UNKNOWN
Classifier: Development Status :: 3 - Alpha
Classifier: Environment :: Web Environment
Classifier: Framework :: Django
Classifier: License :: OSI Approved :: BSD License
Classifier: Operating System :: OS Independent
Classifier: Programming Language :: JavaScript
Classifier: Programming Language :: Python :: 2.7
Classifier: Programming Language :: Python :: 3.3
Classifier: Topic :: Internet :: WWW/HTTP
Classifier: Topic :: Internet :: WWW/HTTP :: Dynamic Content
Classifier: Topic :: Software Development :: Libraries :: Python Modules
Classifier: Topic :: Utilities
